LICENSE
MANIFEST.in
README.rst
setup.cfg
setup.py
django_log_viewer.egg-info/PKG-INFO
django_log_viewer.egg-info/SOURCES.txt
django_log_viewer.egg-info/dependency_links.txt
django_log_viewer.egg-info/not-zip-safe
django_log_viewer.egg-info/top_level.txt
log_viewer/__init__.py
log_viewer/settings.py
log_viewer/urls.py
log_viewer/utils.py
log_viewer/views.py
log_viewer/static/log_viewer/css/jquery.dataTables.min.css
log_viewer/static/log_viewer/css/log-viewer.css
log_viewer/static/log_viewer/images/sort_asc.png
log_viewer/static/log_viewer/images/sort_asc_disabled.png
log_viewer/static/log_viewer/images/sort_both.png
log_viewer/static/log_viewer/images/sort_desc.png
log_viewer/static/log_viewer/images/sort_desc_disabled.png
log_viewer/static/log_viewer/js/jquery.dataTables.min.js
log_viewer/static/log_viewer/js/jquery.min.js
log_viewer/templates/log_viewer/logfile_viewer.html
log_viewer/tests/__init__.py
log_viewer/tests/tests.py
log_viewer/tests/urls.py